<?xml version="1.0" encoding="UTF-8" ?><automobiles><automobile><person_id>8e45be58-dc6c-4330-8b20-e09f80bb5aa9</person_id><license_plate>13-0269B</license_plate><vin>6Y2Y34U56X19K5033</vin><color>DarkSeaGreen</color><year>2024</year></automobile><automobile><person_id>8e45be58-dc6c-4330-8b20-e09f80bb5aa9</person_id><license_plate>SQ 4222</license_plate><vin>8WS43XC31X4SU2234</vin><color>Purple</color><year>1980</year></automobile><automobile><person_id>849c7a53-c718-4f7a-9ee5-3f3fb8c173ee</person_id><license_plate>813-UDW</license_plate><vin>GEHL9C7Z0YCRR4525</vin><color>PapayaWhip</color><year>1999</year></automobile><automobile><person_id>13c45ada-b3ca-4a8c-afae-3d7e98f736f0</person_id><license_plate>MXV 519</license_plate><vin>A17ZW42A4XZR90477</vin><color>Thistle</color><year>2013</year></automobile><automobile><person_id>13c45ada-b3ca-4a8c-afae-3d7e98f736f0</person_id><license_plate>379 HBD</license_plate><vin>1KYJCC7A1K1J53992</vin><color>DarkSlateGray</color><year>2005</year></automobile><automobile><person_id>a9a5cb69-8274-4695-a73b-d166badc556a</person_id><license_plate>ZMZ 181</license_plate><vin>8TCK15W536UY79092</vin><color>GhostWhite</color><year>2019</year></automobile><automobile><person_id>a9a5cb69-8274-4695-a73b-d166badc556a</person_id><license_plate>GJK-378</license_plate><vin>N58ESXWY87LAE5665</vin><color>Peru</color><year>2008</year></automobile><automobile><person_id>8de9abba-590c-40bc-8480-0dc10ea52e44</person_id><license_plate>2N VB537</license_plate><vin>RNAWNLZY21TNW1701</vin><color>Salmon</color><year>1973</year></automobile><automobile><person_id>8de9abba-590c-40bc-8480-0dc10ea52e44</person_id><license_plate>BW 8493</license_plate><vin>V55JGG3V7ZDX70180</vin><color>FloralWhite</color><year>2005</year></automobile><automobile><person_id>7e30b589-bc53-4736-9527-8a353586f1ab</person_id><license_plate>284 IXD</license_plate><vin>T1GHFGC71CKV27073</vin><color>Brown</color><year>1982</year></automobile><automobile><person_id>7dba3e8d-cdaa-4848-9fb8-c340ef847fb8</person_id><license_plate>LQW 808</license_plate><vin>4ENXYU4K8XV3U3257</vin><color>LemonChiffon</color><year>2025</year></automobile><automobile><person_id>ec167dfd-d649-4df3-8541-a82d7bf6315e</person_id><license_plate>SMK8832</license_plate><vin>Y485AT9682F5H6998</vin><color>PaleGreen</color><year>2008</year></automobile><automobile><person_id>e1efea21-7fb2-411b-b8bd-07eacdd693d8</person_id><license_plate>TZD 170</license_plate><vin>RJ783ED27TZNF4312</vin><color>SkyBlue</color><year>2018</year></automobile><automobile><person_id>e1efea21-7fb2-411b-b8bd-07eacdd693d8</person_id><license_plate>31E L05</license_plate><vin>XV3XS1D64H6CG5757</vin><color>Thistle</color><year>1977</year></automobile><automobile><person_id>e1efea21-7fb2-411b-b8bd-07eacdd693d8</person_id><license_plate>CFM 050</license_plate><vin>TZXPMABY14A4P6391</vin><color>Lime</color><year>2024</year></automobile><automobile><person_id>605181ed-989a-4aa2-a352-fea014e22770</person_id><license_plate>528DKU</license_plate><vin>LFZCGBHAX4L2G5128</vin><color>SeaShell</color><year>2014</year></automobile><automobile><person_id>97bb7e64-5778-441f-9b7b-493edf78e87a</person_id><license_plate>02Y-DFTD</license_plate><vin>4G015AAA56K0D3129</vin><color>LightGoldenRodYellow</color><year>1997</year></automobile><automobile><person_id>97bb7e64-5778-441f-9b7b-493edf78e87a</person_id><license_plate>09J 9764</license_plate><vin>R429F5FW1JS453206</vin><color>LightSkyBlue</color><year>2020</year></automobile><automobile><person_id>a0bc934a-0254-47e1-b7a7-3dc9de1e0bfe</person_id><license_plate>253 SB9</license_plate><vin>DUDDADHY0Y6NY9061</vin><color>MediumSlateBlue</color><year>1984</year></automobile><automobile><person_id>a0bc934a-0254-47e1-b7a7-3dc9de1e0bfe</person_id><license_plate>248 AK9</license_plate><vin>VMFXEANPXU1572739</vin><color>SaddleBrown</color><year>1995</year></automobile><automobile><person_id>a0bc934a-0254-47e1-b7a7-3dc9de1e0bfe</person_id><license_plate>432 RIM</license_plate><vin>6V21EC1110CAC6054</vin><color>MediumAquaMarine</color><year>2007</year></automobile><automobile><person_id>ea480f26-cb48-498a-ac11-92f67ce8c528</person_id><license_plate>QPC D84</license_plate><vin>N5GKFJUG4GTSF7155</vin><color>DarkSlateBlue</color><year>2021</year></automobile><automobile><person_id>ea480f26-cb48-498a-ac11-92f67ce8c528</person_id><license_plate>1Y X5850</license_plate><vin>AST0D1GR1BG163427</vin><color>LimeGreen</color><year>2003</year></automobile><automobile><person_id>d6084105-fe48-4b0c-b303-3a175ee19a20</person_id><license_plate>580-FXM</license_plate><vin>6S5T42VG3B17R9350</vin><color>Lime</color><year>1989</year></automobile><automobile><person_id>d6084105-fe48-4b0c-b303-3a175ee19a20</person_id><license_plate>25QJ722</license_plate><vin>7L6B26VVXWBXG6857</vin><color>DarkGray</color><year>2014</year></automobile><automobile><person_id>d6084105-fe48-4b0c-b303-3a175ee19a20</person_id><license_plate>743 OAV</license_plate><vin>EKUHM01G6Z9261599</vin><color>SeaShell</color><year>2005</year></automobile><automobile><person_id>e17d9877-53e0-4ab7-a12e-405dd20777bc</person_id><license_plate>AAK 199</license_plate><vin>LKXDRT6L8E1DK7099</vin><color>DarkGoldenRod</color><year>2022</year></automobile><automobile><person_id>e17d9877-53e0-4ab7-a12e-405dd20777bc</person_id><license_plate>9W UD909</license_plate><vin>L1CPA6AL2REPA8935</vin><color>MintCream</color><year>1995</year></automobile><automobile><person_id>1e083982-73f2-4aed-b270-da294a802948</person_id><license_plate>819 5FM</license_plate><vin>YKFLTHSJ02DTJ6630</vin><color>MediumBlue</color><year>2012</year></automobile><automobile><person_id>1c782b70-d0b3-42d7-bb7a-8297ba2cc028</person_id><license_plate>MIS 150</license_plate><vin>GH3FK1H51B2T09719</vin><color>PaleGoldenRod</color><year>2024</year></automobile><automobile><person_id>85d981f7-314f-4e62-873e-0bc83fe9e127</person_id><license_plate>MIN 811</license_plate><vin>JGVXK06TXY3DK0005</vin><color>GreenYellow</color><year>2013</year></automobile><automobile><person_id>85d981f7-314f-4e62-873e-0bc83fe9e127</person_id><license_plate>9FD 933</license_plate><vin>39RFLKEH53SR78109</vin><color>DarkViolet</color><year>2021</year></automobile><automobile><person_id>85d981f7-314f-4e62-873e-0bc83fe9e127</person_id><license_plate>0VF5102</license_plate><vin>KAT6HSCP9ZKG17739</vin><color>Snow</color><year>2005</year></automobile><automobile><person_id>7313a562-97de-47c2-9427-60bd9f0f3a26</person_id><license_plate>483 DOV</license_plate><vin>UMGEVMRX8A72K0708</vin><color>SlateBlue</color><year>1979</year></automobile><automobile><person_id>cd06134b-7e8d-4315-9355-b3ba17e4bef4</person_id><license_plate>791ILX</license_plate><vin>0TPCNWU80KZT67974</vin><color>AntiqueWhite</color><year>1985</year></automobile><automobile><person_id>cd06134b-7e8d-4315-9355-b3ba17e4bef4</person_id><license_plate>492B</license_plate><vin>FT84BNW332KRF8239</vin><color>GoldenRod</color><year>2016</year></automobile><automobile><person_id>cd06134b-7e8d-4315-9355-b3ba17e4bef4</person_id><license_plate>QZD-470</license_plate><vin>5CFPV2D9806A23384</vin><color>DarkKhaki</color><year>1974</year></automobile><automobile><person_id>ac6b603b-1cf8-4103-ac1a-89617d0d1f05</person_id><license_plate>124 IK5</license_plate><vin>5WM9GB6J99GE65545</vin><color>AntiqueWhite</color><year>2002</year></automobile><automobile><person_id>3eb92105-16c0-452f-9174-22b09e9569b1</person_id><license_plate>UKZ 012</license_plate><vin>GLXYKRXX742J00577</vin><color>WhiteSmoke</color><year>2017</year></automobile><automobile><person_id>d142761b-7846-4960-9bc3-415ab377e338</person_id><license_plate>CRY2457</license_plate><vin>3VXCW36F3R8PK9839</vin><color>BlanchedAlmond</color><year>1996</year></automobile><automobile><person_id>84efea8b-244c-43cf-aaf5-45d2af4436dd</person_id><license_plate>604O</license_plate><vin>3FXW0LH307UW10879</vin><color>Green</color><year>2004</year></automobile><automobile><person_id>9d25f7bd-d65d-4471-ad29-9b96c084ec12</person_id><license_plate>527K1</license_plate><vin>DD8N41PT4K0NB5646</vin><color>DarkRed</color><year>1976</year></automobile><automobile><person_id>68cb9d4b-ae5d-4584-9413-f2ff9cf1fbb7</person_id><license_plate>4LJS945</license_plate><vin>RX2W60KJ7GC2N3524</vin><color>DeepSkyBlue</color><year>2001</year></automobile><automobile><person_id>68cb9d4b-ae5d-4584-9413-f2ff9cf1fbb7</person_id><license_plate>RTQ-9448</license_plate><vin>TRH549K97X2087120</vin><color>HoneyDew</color><year>1982</year></automobile><automobile><person_id>86018583-d262-47f4-badb-79e0fba3a8aa</person_id><license_plate>07-24845</license_plate><vin>FWVTSLK31JN9F3873</vin><color>MediumTurquoise</color><year>1995</year></automobile><automobile><person_id>86018583-d262-47f4-badb-79e0fba3a8aa</person_id><license_plate>7XF1202</license_plate><vin>52F4RDJ40LPDK3184</vin><color>Snow</color><year>2002</year></automobile><automobile><person_id>86018583-d262-47f4-badb-79e0fba3a8aa</person_id><license_plate>95-64488</license_plate><vin>JB5LF3401CRRR8191</vin><color>Plum</color><year>2007</year></automobile><automobile><person_id>6d50805b-cf61-4d4f-9cf5-cde7f0aeafcd</person_id><license_plate>593-QPU</license_plate><vin>F48XT1X00RS5J8360</vin><color>PaleVioletRed</color><year>2004</year></automobile><automobile><person_id>6d50805b-cf61-4d4f-9cf5-cde7f0aeafcd</person_id><license_plate>9466 HF</license_plate><vin>TV69YFDG2TFV57182</vin><color>DarkGreen</color><year>1995</year></automobile><automobile><person_id>c6f7adae-e061-4674-bb38-4cb6812df808</person_id><license_plate>3MM19</license_plate><vin>ZAG4V81298VKN6877</vin><color>PapayaWhip</color><year>1992</year></automobile><automobile><person_id>8297ec0c-7f2b-4310-bb53-77c8b536b15d</person_id><license_plate>515 VNV</license_plate><vin>65JC37SN39NTD5342</vin><color>PapayaWhip</color><year>1984</year></automobile><automobile><person_id>8297ec0c-7f2b-4310-bb53-77c8b536b15d</person_id><license_plate>103 JRX</license_plate><vin>YV6VJ8WY2ZGXR6077</vin><color>Navy</color><year>2022</year></automobile><automobile><person_id>122d6896-aafa-4d16-bba2-20c18739cc55</person_id><license_plate>336 DAK</license_plate><vin>XYDXX3W65D0ZR0197</vin><color>WhiteSmoke</color><year>2011</year></automobile><automobile><person_id>6e6f4eea-2fa7-4335-b50d-1c39ac1a4bfd</person_id><license_plate>4SO2535</license_plate><vin>407XBZB00P9N10406</vin><color>SpringGreen</color><year>2024</year></automobile><automobile><person_id>f2eddf49-69d2-4a3b-bf40-9930c714aad9</person_id><license_plate>ZVP 156</license_plate><vin>03H9YVZM4C7DE6912</vin><color>LimeGreen</color><year>1978</year></automobile><automobile><person_id>f2eddf49-69d2-4a3b-bf40-9930c714aad9</person_id><license_plate>618-PME</license_plate><vin>PXA895TF4V7N23788</vin><color>DarkSalmon</color><year>2011</year></automobile><automobile><person_id>f2eddf49-69d2-4a3b-bf40-9930c714aad9</person_id><license_plate>83X-QTGL</license_plate><vin>F3U845AV6H2147943</vin><color>MistyRose</color><year>2013</year></automobile><automobile><person_id>cc68250a-1dc0-49ca-b635-c89011455d96</person_id><license_plate>96-45332</license_plate><vin>Y6TPMM1D8TD376412</vin><color>Chocolate</color><year>2017</year></automobile><automobile><person_id>cc68250a-1dc0-49ca-b635-c89011455d96</person_id><license_plate>077-FDP</license_plate><vin>6H4FE5EC21MCE0429</vin><color>AliceBlue</color><year>2017</year></automobile><automobile><person_id>724e7bd7-1e77-43c2-aa46-d5b8b28984bd</person_id><license_plate>T82 1ZG</license_plate><vin>BYF863X2X70ZZ3219</vin><color>PaleTurquoise</color><year>1973</year></automobile><automobile><person_id>724e7bd7-1e77-43c2-aa46-d5b8b28984bd</person_id><license_plate>X 534808</license_plate><vin>26GJZYBA9S6G57998</vin><color>Moccasin</color><year>1993</year></automobile><automobile><person_id>7874f5c8-8758-4f1c-b57b-675d1fbc7500</person_id><license_plate>ZHK 605</license_plate><vin>J3D8UV972644M6060</vin><color>PaleGoldenRod</color><year>1991</year></automobile><automobile><person_id>7874f5c8-8758-4f1c-b57b-675d1fbc7500</person_id><license_plate>842 ND6</license_plate><vin>2S5ZN2W78HMFA6741</vin><color>NavajoWhite</color><year>2011</year></automobile><automobile><person_id>5f4599c6-8237-4dac-9dfd-f0b08ed934b7</person_id><license_plate>375-EGKW</license_plate><vin>AJZJWCCG61Z1E5392</vin><color>DarkCyan</color><year>1999</year></automobile><automobile><person_id>5f4599c6-8237-4dac-9dfd-f0b08ed934b7</person_id><license_plate>DWW7987</license_plate><vin>0R1NXAX40YHHX4446</vin><color>LightSeaGreen</color><year>1974</year></automobile><automobile><person_id>2c6e5a32-78da-4f94-b96f-e780f8a8f583</person_id><license_plate>585 AG5</license_plate><vin>K72GSES66G6KA1555</vin><color>DarkSeaGreen</color><year>1971</year></automobile><automobile><person_id>2c6e5a32-78da-4f94-b96f-e780f8a8f583</person_id><license_plate>IWM2018</license_plate><vin>F7HR8FAK4ATV80384</vin><color>AliceBlue</color><year>2012</year></automobile><automobile><person_id>2c6e5a32-78da-4f94-b96f-e780f8a8f583</person_id><license_plate>523 XHX</license_plate><vin>YH0R8WX38WGFP0003</vin><color>LightGreen</color><year>1976</year></automobile><automobile><person_id>94a20700-b75e-4d22-90e1-3d9bb9bcb228</person_id><license_plate>7C 4F4LRF</license_plate><vin>R7F62KEE97A0V7651</vin><color>Pink</color><year>1990</year></automobile><automobile><person_id>f870a608-5f18-4b24-a3a6-07b1e631a08d</person_id><license_plate>5Q YW289</license_plate><vin>HNANGBU87U8D83338</vin><color>DarkGoldenRod</color><year>1993</year></automobile><automobile><person_id>6ef371a8-f5d4-489e-b28d-2ecee1171882</person_id><license_plate>28-J390</license_plate><vin>ZV050PVEXUK0N5285</vin><color>Lavender</color><year>2023</year></automobile><automobile><person_id>6ef371a8-f5d4-489e-b28d-2ecee1171882</person_id><license_plate>805 THN</license_plate><vin>T9W2P03C2AXKW1002</vin><color>Turquoise</color><year>1982</year></automobile><automobile><person_id>945bef86-b51d-4fc8-bbfb-2f415e8ef381</person_id><license_plate>582-QZYQ</license_plate><vin>9Y2AWCLD7XP7J8304</vin><color>OldLace</color><year>2000</year></automobile><automobile><person_id>71935ddc-9440-4c23-834b-e06aa8ebb081</person_id><license_plate>7Q-DUJG</license_plate><vin>91EPLGYU5UH743077</vin><color>Linen</color><year>2013</year></automobile><automobile><person_id>752ad301-8f00-4d74-ba18-ae099c69de34</person_id><license_plate>3VZ S35</license_plate><vin>PLD4BWP01LH682376</vin><color>Lime</color><year>2012</year></automobile><automobile><person_id>153f408b-a071-44ff-84ea-17af38791856</person_id><license_plate>600 PAQ</license_plate><vin>3T6BL0CV19E2V0947</vin><color>Crimson</color><year>1986</year></automobile><automobile><person_id>153f408b-a071-44ff-84ea-17af38791856</person_id><license_plate>BIM 183</license_plate><vin>H8UBXJXY45XWY9857</vin><color>Indigo</color><year>2013</year></automobile><automobile><person_id>4b0fa428-d17b-44c4-87d7-188233c1075b</person_id><license_plate>838 0OB</license_plate><vin>AYNWWLCL0TVW10515</vin><color>LightCoral</color><year>1982</year></automobile><automobile><person_id>4b0fa428-d17b-44c4-87d7-188233c1075b</person_id><license_plate>HWK-426</license_plate><vin>FC1WTL317B6WU2836</vin><color>SpringGreen</color><year>2017</year></automobile><automobile><person_id>4b0fa428-d17b-44c4-87d7-188233c1075b</person_id><license_plate>8ZZ1669</license_plate><vin>K3A9NLX04R1GJ5068</vin><color>Purple</color><year>2010</year></automobile><automobile><person_id>a630ac4a-269f-4b00-9bfe-1c19a3912758</person_id><license_plate>299-VAI</license_plate><vin>66GB938T9P8K95835</vin><color>SeaShell</color><year>2008</year></automobile><automobile><person_id>0345b083-b3ec-4feb-970f-b8a886c0c443</person_id><license_plate>PIN6009</license_plate><vin>6TURL49X81K3Y5273</vin><color>Indigo</color><year>1987</year></automobile><automobile><person_id>bdbc6613-5791-4edd-9477-7b3489e3074b</person_id><license_plate>8HJZ 96</license_plate><vin>GNUA4R711TZ999727</vin><color>PapayaWhip</color><year>2005</year></automobile><automobile><person_id>bdbc6613-5791-4edd-9477-7b3489e3074b</person_id><license_plate>JZJ-566</license_plate><vin>SR86SK023S7GH7077</vin><color>LightSalmon</color><year>1990</year></automobile><automobile><person_id>e30e3c6f-68b2-4cf5-b297-bfe2bf67d2a3</person_id><license_plate>2PB 093</license_plate><vin>Y61GBXE99XK1C0928</vin><color>MediumSeaGreen</color><year>1989</year></automobile><automobile><person_id>5c4178a3-7e32-4ccc-b828-3a5fa727f476</person_id><license_plate>1YW7528</license_plate><vin>DNA265ST2N6U10509</vin><color>SpringGreen</color><year>1981</year></automobile><automobile><person_id>5b9d5c9e-7b32-416c-88a6-7a46a0592a7b</person_id><license_plate>XAO-317</license_plate><vin>YVVEUBFF7RNTF9769</vin><color>BlanchedAlmond</color><year>1982</year></automobile><automobile><person_id>5b9d5c9e-7b32-416c-88a6-7a46a0592a7b</person_id><license_plate>VF 2188</license_plate><vin>NK51LHRY537L31799</vin><color>DarkSeaGreen</color><year>1971</year></automobile><automobile><person_id>5b9d5c9e-7b32-416c-88a6-7a46a0592a7b</person_id><license_plate>V13 9CO</license_plate><vin>MZF47TWM11PZN6063</vin><color>MidnightBlue</color><year>1985</year></automobile><automobile><person_id>7fac970a-544a-443d-aa81-21527c6aebfc</person_id><license_plate>0A FO778</license_plate><vin>JTA1MC5M8U7YS1184</vin><color>GhostWhite</color><year>2021</year></automobile><automobile><person_id>e1041d0e-d579-4142-9ca2-45f579fe527f</person_id><license_plate>TTF-1096</license_plate><vin>A9S4WX9H05RU54733</vin><color>DarkSeaGreen</color><year>2024</year></automobile><automobile><person_id>c7e877c2-9713-4acf-be0f-083a4b0b87e2</person_id><license_plate>HCS-0353</license_plate><vin>VPDAZXFF1S35L1664</vin><color>GoldenRod</color><year>1982</year></automobile><automobile><person_id>c7e877c2-9713-4acf-be0f-083a4b0b87e2</person_id><license_plate>443 RU3</license_plate><vin>5YX358LN5DJBW7231</vin><color>DarkCyan</color><year>1971</year></automobile><automobile><person_id>3cb3d65f-83c8-4015-8f9a-99f6929f9fe9</person_id><license_plate>314JC</license_plate><vin>YPT8XYF371S0G1983</vin><color>AntiqueWhite</color><year>1980</year></automobile><automobile><person_id>3cb3d65f-83c8-4015-8f9a-99f6929f9fe9</person_id><license_plate>8VG 605</license_plate><vin>F56TUD9E77NUN6405</vin><color>Navy</color><year>2023</year></automobile><automobile><person_id>3514f13c-8c9c-4bf8-949a-5f862ed06e94</person_id><license_plate>KCX 384</license_plate><vin>MZNE4BGN40WKM7702</vin><color>Pink</color><year>1989</year></automobile><automobile><person_id>3514f13c-8c9c-4bf8-949a-5f862ed06e94</person_id><license_plate>6KO F58</license_plate><vin>84CT9JVHXV3050920</vin><color>SeaShell</color><year>2001</year></automobile><automobile><person_id>c788d593-b9e2-4ada-ad27-8437cd976f3e</person_id><license_plate>5TA 641</license_plate><vin>VDY3K0ED6EP332231</vin><color>DarkOrchid</color><year>1997</year></automobile><automobile><person_id>874a7c64-b1bf-4334-a209-cf7b73b132ec</person_id><license_plate>24Z-ERVT</license_plate><vin>V6W1R7BZ9K8306268</vin><color>Maroon</color><year>2024</year></automobile><automobile><person_id>874a7c64-b1bf-4334-a209-cf7b73b132ec</person_id><license_plate>70W AW0</license_plate><vin>GWHEKY2H459HA0210</vin><color>Salmon</color><year>1993</year></automobile><automobile><person_id>3b00e43d-2e86-4309-9741-ccfd7b2c9efc</person_id><license_plate>X54-03C</license_plate><vin>3UDGGL998B7TG5388</vin><color>Green</color><year>1984</year></automobile><automobile><person_id>5d3cba9a-e161-4ebb-bfe3-a262d960a676</person_id><license_plate>63ZL6</license_plate><vin>3SHWKC2K4K9S36797</vin><color>Moccasin</color><year>1971</year></automobile><automobile><person_id>5d3cba9a-e161-4ebb-bfe3-a262d960a676</person_id><license_plate>DHT V77</license_plate><vin>YW8XDH4976LTH3449</vin><color>LemonChiffon</color><year>1982</year></automobile><automobile><person_id>435e625e-408c-43ab-977e-561766f58468</person_id><license_plate>48-J201</license_plate><vin>8PCS4ZGK0E5LW6874</vin><color>LightSlateGray</color><year>2010</year></automobile><automobile><person_id>53fc8e1a-6047-4434-8736-cadaedbfc4b1</person_id><license_plate>4O 35706</license_plate><vin>2TYAAPWT4W55Y3298</vin><color>Teal</color><year>2009</year></automobile><automobile><person_id>b1ef34b7-812c-474f-9cb5-2aafa18f4d2d</person_id><license_plate>AER3048</license_plate><vin>K5R762NF6MZXY5402</vin><color>DarkSalmon</color><year>1988</year></automobile><automobile><person_id>b1ef34b7-812c-474f-9cb5-2aafa18f4d2d</person_id><license_plate>699 DLP</license_plate><vin>LUFWXDA67J8L97854</vin><color>OliveDrab</color><year>2022</year></automobile><automobile><person_id>486aa157-9628-49a1-bcb6-7d8de9493d41</person_id><license_plate>490 GTI</license_plate><vin>BS0YB39P0JZ9X5733</vin><color>DimGray</color><year>2014</year></automobile><automobile><person_id>bb237593-bf91-4453-9476-a2c4854e712b</person_id><license_plate>675-UEX</license_plate><vin>0MMY0TH21RE3R9813</vin><color>CadetBlue</color><year>1996</year></automobile><automobile><person_id>bb237593-bf91-4453-9476-a2c4854e712b</person_id><license_plate>INA 711</license_plate><vin>CTZNKNAK7T7710018</vin><color>DarkRed</color><year>1971</year></automobile><automobile><person_id>a078cca7-cf59-46a6-87f1-251511ff4412</person_id><license_plate>455-XJN</license_plate><vin>N1MFDTKE9J6ES2961</vin><color>WhiteSmoke</color><year>1992</year></automobile><automobile><person_id>a078cca7-cf59-46a6-87f1-251511ff4412</person_id><license_plate>LOD 624</license_plate><vin>CN5T4EN50GVEX4619</vin><color>GoldenRod</color><year>2025</year></automobile><automobile><person_id>5d7a1a6b-ce77-41aa-9d46-3ee9c84d466a</person_id><license_plate>9-45386N</license_plate><vin>34HEJHVJ4K0ZJ4621</vin><color>IndianRed</color><year>1997</year></automobile><automobile><person_id>f0959d02-a65f-456a-955a-2230b73ab6e5</person_id><license_plate>B 335334</license_plate><vin>1DF56BZH0N76D9508</vin><color>DarkMagenta</color><year>2019</year></automobile><automobile><person_id>a988b8c6-3b9b-4dc0-abae-fd3c079b6383</person_id><license_plate>LXV 763</license_plate><vin>14YMXVR406JCP4693</vin><color>MediumSeaGreen</color><year>2001</year></automobile><automobile><person_id>a988b8c6-3b9b-4dc0-abae-fd3c079b6383</person_id><license_plate>EA2 4128</license_plate><vin>B2FLV12PXKTA04073</vin><color>ForestGreen</color><year>1979</year></automobile><automobile><person_id>e1faa1ff-2e83-4d3e-86c7-bd172430b321</person_id><license_plate>QBP-620</license_plate><vin>0N0MBCEJ5Y1980178</vin><color>MediumSeaGreen</color><year>2018</year></automobile><automobile><person_id>e1faa1ff-2e83-4d3e-86c7-bd172430b321</person_id><license_plate>IR 21639</license_plate><vin>KUGGM8G2XHS212459</vin><color>Magenta</color><year>1988</year></automobile><automobile><person_id>5116dfb7-561d-49bb-85b4-551d074269d2</person_id><license_plate>ZOO 437</license_plate><vin>ANZ4RGSV560HP0909</vin><color>White</color><year>1974</year></automobile><automobile><person_id>5116dfb7-561d-49bb-85b4-551d074269d2</person_id><license_plate>LVD 498</license_plate><vin>BH1DVFRF84FS92583</vin><color>HoneyDew</color><year>1984</year></automobile><automobile><person_id>acee2ce8-c715-474a-93ba-81000ccdf7f3</person_id><license_plate>DQ 5070</license_plate><vin>746USJGV9Z0RF3017</vin><color>Beige</color><year>1973</year></automobile><automobile><person_id>acee2ce8-c715-474a-93ba-81000ccdf7f3</person_id><license_plate>78-M145</license_plate><vin>PY0ZUAFPX247L8922</vin><color>RosyBrown</color><year>1973</year></automobile><automobile><person_id>146a4163-b96b-472d-a041-ca53b2925a0b</person_id><license_plate>MST 663</license_plate><vin>7HVL54HW2BZUZ5516</vin><color>DarkBlue</color><year>1988</year></automobile><automobile><person_id>146a4163-b96b-472d-a041-ca53b2925a0b</person_id><license_plate>NF-8330</license_plate><vin>4GUB2A7CX7AC38934</vin><color>GreenYellow</color><year>2015</year></automobile><automobile><person_id>146a4163-b96b-472d-a041-ca53b2925a0b</person_id><license_plate>741 NKO</license_plate><vin>KM637FEHX9MH88051</vin><color>Lavender</color><year>1984</year></automobile></automobiles>